shreyadatta/__init__.py
shreyadatta-0.3.dist-info/LICENSE
shreyadatta-0.3.dist-info/METADATA
shreyadatta-0.3.dist-info/WHEEL
shreyadatta-0.3.dist-info/top_level.txt
shreyadatta-0.3.dist-info/RECORD
